examples/import_csv/generate_vectors.py
milvus_cli/AliasClient.py
milvus_cli/CliClient.py
milvus_cli/CollectionClient.py
milvus_cli/ConnectionClient.py
milvus_cli/DataClient.py
milvus_cli/DatabaseClient.py
milvus_cli/Fs.py
milvus_cli/IndexClient.py
milvus_cli/OutputFormatter.py
milvus_cli/PartitionClient.py
milvus_cli/PrivilegeGroup.py
milvus_cli/ResourceGroup.py
milvus_cli/RoleClient.py
milvus_cli/Types.py
milvus_cli/UserClient.py
milvus_cli/Validation.py
milvus_cli/__init__.py
milvus_cli/history.py
milvus_cli/main.py
milvus_cli/prompt_style.py
milvus_cli/utils.py
milvus_cli/scripts/__init__.py
milvus_cli/scripts/alias_client_cli.py
milvus_cli/scripts/collection_client_cli.py
milvus_cli/scripts/connection_cli.py
milvus_cli/scripts/connection_client_cli.py
milvus_cli/scripts/data_client_cli.py
milvus_cli/scripts/database_client_cli.py
milvus_cli/scripts/helper_cli.py
milvus_cli/scripts/helper_client_cli.py
milvus_cli/scripts/index_client_cli.py
milvus_cli/scripts/init_client_cli.py
milvus_cli/scripts/milvus_cli.py
milvus_cli/scripts/milvus_client_cli.py
milvus_cli/scripts/partition_client_cli.py
milvus_cli/scripts/privilege_group_cli.py
milvus_cli/scripts/resource_group_cli.py
milvus_cli/scripts/role_client_cli.py
milvus_cli/scripts/user_client_cli.py
milvus_cli/test/test_alias_client.py
milvus_cli/test/test_cli_client.py
milvus_cli/test/test_collection_client.py
milvus_cli/test/test_config.py
milvus_cli/test/test_connection_client.py
milvus_cli/test/test_data_client.py
milvus_cli/test/test_database_client.py
milvus_cli/test/test_index_client.py
milvus_cli/test/test_partition_client.py
milvus_cli/test/test_role_client.py
milvus_cli/test/test_user_client.py
tests/conftest.py
tests/run_integration_tests.py
tests/test_alias.py
tests/test_collection.py
tests/test_connection.py
tests/test_data.py
tests/test_database.py
tests/test_hybrid_search_query_iterator.py
tests/test_index.py
tests/test_new_features_integration.py
tests/test_partition.py
milvus_cli-1.2.0.dist-info/LICENSE
milvus_cli-1.2.0.dist-info/METADATA
milvus_cli-1.2.0.dist-info/WHEEL
milvus_cli-1.2.0.dist-info/entry_points.txt
milvus_cli-1.2.0.dist-info/top_level.txt
milvus_cli-1.2.0.dist-info/RECORD
