Metadata-Version: 2.1
Name: milvus_cli
Version: 1.2.0
Summary: CLI for Milvus
Home-page: https://github.com/zilliztech/milvus_cli
Author: Milvus Team
Author-email: milvus-team@zilliz.com
License: Apache-2.0
Requires-Python: >=3.8
License-File: LICENSE
Requires-Dist: Click ==8.0.1
Requires-Dist: pymilvus >=2.5.0
Requires-Dist: tabulate ==0.8.9
Requires-Dist: requests ==2.31.0
Requires-Dist: prompt-toolkit >=3.0.0
